ndinterp-0.0.1.dist-info/METADATA
ndinterp-0.0.1.dist-info/WHEEL
ndinterp/__init__.py
ndinterp/ndinterp.pypy37-pp73-x86_64-linux-gnu.so
ndinterp-0.0.1.dist-info/RECORD
